ape_ganache/__init__.py
ape_ganache/exceptions.py
ape_ganache/provider.py
ape_ganache/py.typed
ape_ganache/version.py
ape_ganache-0.7.0.dist-info/LICENSE
ape_ganache-0.7.0.dist-info/METADATA
ape_ganache-0.7.0.dist-info/WHEEL
ape_ganache-0.7.0.dist-info/top_level.txt
ape_ganache-0.7.0.dist-info/RECORD
